{
  "minimal-style@@embed-hide-title": false,
  "minimal-style@@embed-strict": true,
  "minimal-style@@bold-color@@dark": "#DA702C",
  "minimal-style@@italic-color@@dark": "#879A39",
  "minimal-style@@h2-color@@dark": "#CE5D97",
  "minimal-style@@h3-color@@dark": "#8B7EC8",
  "minimal-style@@file-header-visibility": "minimal-tab-title-hover",
  "minimal-style@@inline-title-color@@dark": "#4385BE",
  "minimal-style@@window-title-off": false,
  "minimal-style@@minimal-tab-text-color-active@@dark": "#4385BE",
  "minimal-style@@h2-l": true
}